acenda/__init__.py
acenda-0.1.0.dist-info/WHEEL
acenda-0.1.0.dist-info/METADATA
acenda-0.1.0.dist-info/RECORD
