Metadata-Version: 2.1
Name: acenda
Version: 0.1.0
Summary: acenda python sdk
Home-page: https://github.com/nicksherron/acenda-python-sdk
Author: nicksherron
Author-email: nsherron90@gmail.com
Requires-Python: >=3.6,<4.0
Classifier: Programming Language :: Python :: 3
Classifier: Programming Language :: Python :: 3.6
Classifier: Programming Language :: Python :: 3.7
Classifier: Programming Language :: Python :: 3.8
Project-URL: Repository, https://github.com/nicksherron/acenda-python-sdk
